<?xml version="1.0" ?>
<font name="dec_terminal_modern" width="64" language="latin">
  <character uvIndex="0" character="!" byte="33" type="special">
    <regular x="4" y="0" width="30"/>
    <bold x="4" y="0" width="30"/>
    <italic x="33" y="0" width="20"/>
    <boldItalic x="30" y="0" width="25"/>
  </character>
  <character uvIndex="1" character="&quot;" byte="34" type="special">
    <regular x="42" y="0" width="30"/>
    <bold x="46" y="0" width="30"/>
    <italic x="163" y="0" width="21"/>
    <boldItalic x="160" y="0" width="26"/>
  </character>
  <character uvIndex="2" character="#" byte="35" type="special">
    <regular x="80" y="0" width="30"/>
    <bold x="88" y="0" width="30"/>
    <italic x="282" y="0" width="30"/>
    <boldItalic x="279" y="0" width="35"/>
  </character>
  <character uvIndex="3" character="$" byte="36" type="special">
    <regular x="118" y="0" width="30"/>
    <bold x="130" y="0" width="30"/>
    <italic x="412" y="0" width="29"/>
    <boldItalic x="409" y="0" width="35"/>
  </character>
  <character uvIndex="4" character="%" byte="37" type="special">
    <regular x="156" y="0" width="30"/>
    <bold x="172" y="0" width="30"/>
    <italic x="535" y="0" width="40"/>
    <boldItalic x="532" y="0" width="45"/>
  </character>
  <character uvIndex="5" character="&amp;" byte="38" type="special">
    <regular x="194" y="0" width="30"/>
    <bold x="214" y="0" width="30"/>
    <italic x="665" y="0" width="29"/>
    <boldItalic x="663" y="0" width="33"/>
  </character>
  <character uvIndex="6" character="'" byte="39" type="special">
    <regular x="232" y="0" width="30"/>
    <bold x="256" y="0" width="30"/>
    <italic x="805" y="0" width="19"/>
    <boldItalic x="803" y="0" width="23"/>
  </character>
  <character uvIndex="7" character="(" byte="40" type="special">
    <regular x="270" y="0" width="30"/>
    <bold x="298" y="0" width="30"/>
    <italic x="930" y="0" width="22"/>
    <boldItalic x="928" y="0" width="27"/>
  </character>
  <character uvIndex="8" character=")" byte="41" type="special">
    <regular x="308" y="0" width="30"/>
    <bold x="340" y="0" width="30"/>
    <italic x="1054" y="0" width="21"/>
    <boldItalic x="1051" y="0" width="26"/>
  </character>
  <character uvIndex="9" character="*" byte="42" type="special">
    <regular x="346" y="0" width="30"/>
    <bold x="382" y="0" width="30"/>
    <italic x="1180" y="0" width="29"/>
    <boldItalic x="1178" y="0" width="33"/>
  </character>
  <character uvIndex="10" character="+" byte="43" type="special">
    <regular x="384" y="0" width="30"/>
    <bold x="424" y="0" width="30"/>
    <italic x="1309" y="0" width="27"/>
    <boldItalic x="1307" y="0" width="32"/>
  </character>
  <character uvIndex="11" character="," byte="44" type="special">
    <regular x="422" y="0" width="30"/>
    <bold x="466" y="0" width="30"/>
    <italic x="1431" y="0" width="19"/>
    <boldItalic x="1429" y="0" width="23"/>
  </character>
  <character uvIndex="12" character="-" byte="45" type="special">
    <regular x="460" y="0" width="30"/>
    <bold x="508" y="0" width="30"/>
    <italic x="1565" y="0" width="28"/>
    <boldItalic x="1563" y="0" width="32"/>
  </character>
  <character uvIndex="13" character="." byte="46" type="special">
    <regular x="498" y="0" width="30"/>
    <bold x="550" y="0" width="30"/>
    <italic x="1694" y="0" width="12"/>
    <boldItalic x="1691" y="0" width="17"/>
  </character>
  <character uvIndex="14" character="/" byte="47" type="special">
    <regular x="536" y="0" width="30"/>
    <bold x="592" y="0" width="30"/>
    <italic x="1815" y="0" width="40"/>
    <boldItalic x="1812" y="0" width="45"/>
  </character>
  <character uvIndex="15" character="0" byte="48" type="numerical">
    <regular x="574" y="0" width="30"/>
    <bold x="634" y="0" width="30"/>
    <italic x="1947" y="0" width="31"/>
    <boldItalic x="1945" y="0" width="35"/>
  </character>
  <character uvIndex="16" character="1" byte="49" type="numerical">
    <regular x="612" y="0" width="30"/>
    <bold x="676" y="0" width="30"/>
    <italic x="2074" y="0" width="27"/>
    <boldItalic x="2071" y="0" width="32"/>
  </character>
  <character uvIndex="17" character="2" byte="50" type="numerical">
    <regular x="650" y="0" width="30"/>
    <bold x="718" y="0" width="30"/>
    <italic x="2199" y="0" width="37"/>
    <boldItalic x="2196" y="0" width="42"/>
  </character>
  <character uvIndex="18" character="3" byte="51" type="numerical">
    <regular x="688" y="0" width="30"/>
    <bold x="760" y="0" width="30"/>
    <italic x="2329" y="0" width="38"/>
    <boldItalic x="2327" y="0" width="42"/>
  </character>
  <character uvIndex="19" character="4" byte="52" type="numerical">
    <regular x="726" y="0" width="30"/>
    <bold x="802" y="0" width="30"/>
    <italic x="2459" y="0" width="29"/>
    <boldItalic x="2456" y="0" width="34"/>
  </character>
  <character uvIndex="20" character="5" byte="53" type="numerical">
    <regular x="764" y="0" width="30"/>
    <bold x="844" y="0" width="30"/>
    <italic x="2585" y="0" width="38"/>
    <boldItalic x="2583" y="0" width="42"/>
  </character>
  <character uvIndex="21" character="6" byte="54" type="numerical">
    <regular x="802" y="0" width="30"/>
    <bold x="886" y="0" width="30"/>
    <italic x="2713" y="0" width="35"/>
    <boldItalic x="2711" y="0" width="39"/>
  </character>
  <character uvIndex="22" character="7" byte="55" type="numerical">
    <regular x="840" y="0" width="30"/>
    <bold x="928" y="0" width="30"/>
    <italic x="2846" y="0" width="33"/>
    <boldItalic x="2843" y="0" width="38"/>
  </character>
  <character uvIndex="23" character="8" byte="56" type="numerical">
    <regular x="878" y="0" width="30"/>
    <bold x="970" y="0" width="30"/>
    <italic x="2969" y="0" width="35"/>
    <boldItalic x="2967" y="0" width="39"/>
  </character>
  <character uvIndex="24" character="9" byte="57" type="numerical">
    <regular x="916" y="0" width="30"/>
    <bold x="1012" y="0" width="30"/>
    <italic x="3098" y="0" width="34"/>
    <boldItalic x="3096" y="0" width="38"/>
  </character>
  <character uvIndex="25" character=":" byte="58" type="special">
    <regular x="954" y="0" width="30"/>
    <bold x="1054" y="0" width="30"/>
    <italic x="3230" y="0" width="20"/>
    <boldItalic x="3227" y="0" width="26"/>
  </character>
  <character uvIndex="26" character=";" byte="59" type="special">
    <regular x="992" y="0" width="30"/>
    <bold x="1096" y="0" width="30"/>
    <italic x="3351" y="0" width="27"/>
    <boldItalic x="3349" y="0" width="32"/>
  </character>
  <character uvIndex="27" character="&lt;" byte="60" type="special">
    <regular x="1030" y="0" width="30"/>
    <bold x="1138" y="0" width="30"/>
    <italic x="3486" y="0" width="33"/>
    <boldItalic x="3484" y="0" width="37"/>
  </character>
  <character uvIndex="28" character="=" byte="61" type="special">
    <regular x="1068" y="0" width="30"/>
    <bold x="1180" y="0" width="30"/>
    <italic x="3611" y="0" width="31"/>
    <boldItalic x="3609" y="0" width="36"/>
  </character>
  <character uvIndex="29" character="&gt;" byte="62" type="special">
    <regular x="1106" y="0" width="30"/>
    <bold x="1222" y="0" width="30"/>
    <italic x="3735" y="0" width="32"/>
    <boldItalic x="3732" y="0" width="37"/>
  </character>
  <character uvIndex="30" character="?" byte="63" type="special">
    <regular x="1144" y="0" width="30"/>
    <bold x="1264" y="0" width="30"/>
    <italic x="3873" y="0" width="28"/>
    <boldItalic x="3870" y="0" width="33"/>
  </character>
  <character uvIndex="31" character="@" byte="64" type="special">
    <regular x="1182" y="0" width="30"/>
    <bold x="1306" y="0" width="30"/>
    <italic x="3994" y="0" width="34"/>
    <boldItalic x="3992" y="0" width="38"/>
  </character>
  <character uvIndex="32" character="A" byte="65" type="alphabetical">
    <regular x="1220" y="0" width="30"/>
    <bold x="1348" y="0" width="30"/>
    <italic x="4119" y="0" width="33"/>
    <boldItalic x="4116" y="0" width="38"/>
  </character>
  <character uvIndex="33" character="B" byte="66" type="alphabetical">
    <regular x="1258" y="0" width="30"/>
    <bold x="1390" y="0" width="30"/>
    <italic x="4247" y="0" width="37"/>
    <boldItalic x="4245" y="0" width="41"/>
  </character>
  <character uvIndex="34" character="C" byte="67" type="alphabetical">
    <regular x="1296" y="0" width="30"/>
    <bold x="1432" y="0" width="30"/>
    <italic x="4379" y="0" width="33"/>
    <boldItalic x="4377" y="0" width="37"/>
  </character>
  <character uvIndex="35" character="D" byte="68" type="alphabetical">
    <regular x="1334" y="0" width="30"/>
    <bold x="1474" y="0" width="30"/>
    <italic x="4503" y="0" width="35"/>
    <boldItalic x="4501" y="0" width="39"/>
  </character>
  <character uvIndex="36" character="E" byte="69" type="alphabetical">
    <regular x="1372" y="0" width="30"/>
    <bold x="1516" y="0" width="30"/>
    <italic x="4631" y="0" width="40"/>
    <boldItalic x="4628" y="0" width="45"/>
  </character>
  <character uvIndex="37" character="F" byte="70" type="alphabetical">
    <regular x="1410" y="0" width="30"/>
    <bold x="1558" y="0" width="30"/>
    <italic x="4759" y="0" width="40"/>
    <boldItalic x="4756" y="0" width="45"/>
  </character>
  <character uvIndex="38" character="G" byte="71" type="alphabetical">
    <regular x="1448" y="0" width="30"/>
    <bold x="1600" y="0" width="30"/>
    <italic x="4891" y="0" width="32"/>
    <boldItalic x="4889" y="0" width="36"/>
  </character>
  <character uvIndex="39" character="H" byte="72" type="alphabetical">
    <regular x="1486" y="0" width="30"/>
    <bold x="1642" y="0" width="30"/>
    <italic x="5015" y="0" width="40"/>
    <boldItalic x="5012" y="0" width="45"/>
  </character>
  <character uvIndex="40" character="I" byte="73" type="alphabetical">
    <regular x="1524" y="0" width="30"/>
    <bold x="1684" y="0" width="30"/>
    <italic x="5146" y="0" width="33"/>
    <boldItalic x="5143" y="0" width="38"/>
  </character>
  <character uvIndex="41" character="J" byte="74" type="alphabetical">
    <regular x="1562" y="0" width="30"/>
    <bold x="1726" y="0" width="30"/>
    <italic x="5273" y="0" width="38"/>
    <boldItalic x="5271" y="0" width="42"/>
  </character>
  <character uvIndex="42" character="K" byte="75" type="alphabetical">
    <regular x="1600" y="0" width="30"/>
    <bold x="1768" y="0" width="30"/>
    <italic x="5399" y="0" width="40"/>
    <boldItalic x="5396" y="0" width="45"/>
  </character>
  <character uvIndex="43" character="L" byte="76" type="alphabetical">
    <regular x="1638" y="0" width="30"/>
    <bold x="1810" y="0" width="30"/>
    <italic x="5527" y="0" width="27"/>
    <boldItalic x="5524" y="0" width="32"/>
  </character>
  <character uvIndex="44" character="M" byte="77" type="alphabetical">
    <regular x="1676" y="0" width="30"/>
    <bold x="1852" y="0" width="30"/>
    <italic x="5655" y="0" width="40"/>
    <boldItalic x="5652" y="0" width="45"/>
  </character>
  <character uvIndex="45" character="N" byte="78" type="alphabetical">
    <regular x="1714" y="0" width="30"/>
    <bold x="1894" y="0" width="30"/>
    <italic x="5783" y="0" width="40"/>
    <boldItalic x="5780" y="0" width="45"/>
  </character>
  <character uvIndex="46" character="O" byte="79" type="alphabetical">
    <regular x="1752" y="0" width="30"/>
    <bold x="1936" y="0" width="30"/>
    <italic x="5914" y="0" width="34"/>
    <boldItalic x="5912" y="0" width="38"/>
  </character>
  <character uvIndex="47" character="P" byte="80" type="alphabetical">
    <regular x="1790" y="0" width="30"/>
    <bold x="1978" y="0" width="30"/>
    <italic x="6039" y="0" width="37"/>
    <boldItalic x="6036" y="0" width="42"/>
  </character>
  <character uvIndex="48" character="Q" byte="81" type="alphabetical">
    <regular x="1828" y="0" width="30"/>
    <bold x="2020" y="0" width="30"/>
    <italic x="6170" y="0" width="34"/>
    <boldItalic x="6168" y="0" width="38"/>
  </character>
  <character uvIndex="49" character="R" byte="82" type="alphabetical">
    <regular x="1866" y="0" width="30"/>
    <bold x="2062" y="0" width="30"/>
    <italic x="6295" y="0" width="37"/>
    <boldItalic x="6292" y="0" width="42"/>
  </character>
  <character uvIndex="50" character="S" byte="83" type="alphabetical">
    <regular x="1904" y="0" width="30"/>
    <bold x="2104" y="0" width="30"/>
    <italic x="6425" y="0" width="35"/>
    <boldItalic x="6423" y="0" width="39"/>
  </character>
  <character uvIndex="51" character="T" byte="84" type="alphabetical">
    <regular x="1942" y="0" width="30"/>
    <bold x="2146" y="0" width="30"/>
    <italic x="6561" y="0" width="30"/>
    <boldItalic x="6558" y="0" width="35"/>
  </character>
  <character uvIndex="52" character="U" byte="85" type="alphabetical">
    <regular x="1980" y="0" width="30"/>
    <bold x="2188" y="0" width="30"/>
    <italic x="6682" y="0" width="37"/>
    <boldItalic x="6680" y="0" width="41"/>
  </character>
  <character uvIndex="53" character="V" byte="86" type="alphabetical">
    <regular x="2018" y="0" width="30"/>
    <bold x="2230" y="0" width="30"/>
    <italic x="6817" y="0" width="30"/>
    <boldItalic x="6815" y="0" width="34"/>
  </character>
  <character uvIndex="54" character="W" byte="87" type="alphabetical">
    <regular x="2056" y="0" width="30"/>
    <bold x="2272" y="0" width="30"/>
    <italic x="6937" y="0" width="38"/>
    <boldItalic x="6935" y="0" width="42"/>
  </character>
  <character uvIndex="55" character="X" byte="88" type="alphabetical">
    <regular x="2094" y="0" width="30"/>
    <bold x="2314" y="0" width="30"/>
    <italic x="7063" y="0" width="40"/>
    <boldItalic x="7060" y="0" width="45"/>
  </character>
  <character uvIndex="56" character="Y" byte="89" type="alphabetical">
    <regular x="2132" y="0" width="30"/>
    <bold x="2356" y="0" width="30"/>
    <italic x="7201" y="0" width="30"/>
    <boldItalic x="7198" y="0" width="35"/>
  </character>
  <character uvIndex="57" character="Z" byte="90" type="alphabetical">
    <regular x="2170" y="0" width="30"/>
    <bold x="2398" y="0" width="30"/>
    <italic x="7319" y="0" width="40"/>
    <boldItalic x="7316" y="0" width="45"/>
  </character>
  <character uvIndex="58" character="[" byte="91" type="special">
    <regular x="2208" y="0" width="30"/>
    <bold x="2440" y="0" width="30"/>
    <italic x="7454" y="0" width="30"/>
    <boldItalic x="7451" y="0" width="35"/>
  </character>
  <character uvIndex="59" character="\" byte="92" type="special">
    <regular x="2246" y="0" width="30"/>
    <bold x="2482" y="0" width="30"/>
    <italic x="7588" y="0" width="13"/>
    <boldItalic x="7586" y="0" width="17"/>
  </character>
  <character uvIndex="60" character="]" byte="93" type="special">
    <regular x="2284" y="0" width="30"/>
    <bold x="2524" y="0" width="30"/>
    <italic x="7706" y="0" width="30"/>
    <boldItalic x="7703" y="0" width="35"/>
  </character>
  <character uvIndex="61" character="^" byte="94" type="special">
    <regular x="2322" y="0" width="30"/>
    <bold x="2566" y="0" width="30"/>
    <italic x="7837" y="0" width="27"/>
    <boldItalic x="7835" y="0" width="31"/>
  </character>
  <character uvIndex="62" character="_" byte="95" type="special">
    <regular x="2360" y="0" width="30"/>
    <bold x="2608" y="0" width="30"/>
    <italic x="7959" y="0" width="27"/>
    <boldItalic x="7956" y="0" width="32"/>
  </character>
  <character uvIndex="63" character="`" byte="96" type="special">
    <regular x="2398" y="0" width="30"/>
    <bold x="2650" y="0" width="30"/>
    <italic x="8106" y="0" width="11"/>
    <boldItalic x="8104" y="0" width="15"/>
  </character>
  <character uvIndex="64" character="a" byte="97" type="alphabetical">
    <regular x="2436" y="0" width="30"/>
    <bold x="2692" y="0" width="30"/>
    <italic x="24" y="128" width="33"/>
    <boldItalic x="22" y="128" width="37"/>
  </character>
  <character uvIndex="65" character="b" byte="98" type="alphabetical">
    <regular x="2474" y="0" width="30"/>
    <bold x="2734" y="0" width="30"/>
    <italic x="151" y="128" width="32"/>
    <boldItalic x="148" y="128" width="37"/>
  </character>
  <character uvIndex="66" character="c" byte="99" type="alphabetical">
    <regular x="2512" y="0" width="30"/>
    <bold x="2776" y="0" width="30"/>
    <italic x="282" y="128" width="30"/>
    <boldItalic x="280" y="128" width="34"/>
  </character>
  <character uvIndex="67" character="d" byte="100" type="alphabetical">
    <regular x="2550" y="0" width="30"/>
    <bold x="2818" y="0" width="30"/>
    <italic x="410" y="128" width="37"/>
    <boldItalic x="408" y="128" width="41"/>
  </character>
  <character uvIndex="68" character="e" byte="101" type="alphabetical">
    <regular x="2588" y="0" width="30"/>
    <bold x="2860" y="0" width="30"/>
    <italic x="538" y="128" width="30"/>
    <boldItalic x="536" y="128" width="34"/>
  </character>
  <character uvIndex="69" character="f" byte="102" type="alphabetical">
    <regular x="2626" y="0" width="30"/>
    <bold x="2902" y="0" width="30"/>
    <italic x="669" y="128" width="31"/>
    <boldItalic x="667" y="128" width="35"/>
  </character>
  <character uvIndex="70" character="g" byte="103" type="alphabetical">
    <regular x="2664" y="0" width="30"/>
    <bold x="2944" y="0" width="30"/>
    <italic x="788" y="128" width="38"/>
    <boldItalic x="786" y="128" width="43"/>
  </character>
  <character uvIndex="71" character="h" byte="104" type="alphabetical">
    <regular x="2702" y="0" width="30"/>
    <bold x="2986" y="0" width="30"/>
    <italic x="919" y="128" width="32"/>
    <boldItalic x="916" y="128" width="37"/>
  </character>
  <character uvIndex="72" character="i" byte="105" type="alphabetical">
    <regular x="2740" y="0" width="30"/>
    <bold x="3028" y="0" width="30"/>
    <italic x="1050" y="128" width="27"/>
    <boldItalic x="1047" y="128" width="32"/>
  </character>
  <character uvIndex="73" character="j" byte="106" type="alphabetical">
    <regular x="2778" y="0" width="30"/>
    <bold x="3070" y="0" width="30"/>
    <italic x="1172" y="128" width="39"/>
    <boldItalic x="1170" y="128" width="43"/>
  </character>
  <character uvIndex="74" character="k" byte="107" type="alphabetical">
    <regular x="2816" y="0" width="30"/>
    <bold x="3112" y="0" width="30"/>
    <italic x="1303" y="128" width="28"/>
    <boldItalic x="1300" y="128" width="34"/>
  </character>
  <character uvIndex="75" character="l" byte="108" type="alphabetical">
    <regular x="2854" y="0" width="30"/>
    <bold x="3154" y="0" width="30"/>
    <italic x="1438" y="128" width="23"/>
    <boldItalic x="1435" y="128" width="28"/>
  </character>
  <character uvIndex="76" character="m" byte="109" type="alphabetical">
    <regular x="2892" y="0" width="30"/>
    <bold x="3196" y="0" width="30"/>
    <italic x="1559" y="128" width="33"/>
    <boldItalic x="1556" y="128" width="39"/>
  </character>
  <character uvIndex="77" character="n" byte="110" type="alphabetical">
    <regular x="2930" y="0" width="30"/>
    <bold x="3238" y="0" width="30"/>
    <italic x="1687" y="128" width="32"/>
    <boldItalic x="1684" y="128" width="37"/>
  </character>
  <character uvIndex="78" character="o" byte="111" type="alphabetical">
    <regular x="2968" y="0" width="30"/>
    <bold x="3280" y="0" width="30"/>
    <italic x="1818" y="128" width="29"/>
    <boldItalic x="1816" y="128" width="33"/>
  </character>
  <character uvIndex="79" character="p" byte="112" type="alphabetical">
    <regular x="3006" y="0" width="30"/>
    <bold x="3322" y="0" width="30"/>
    <italic x="1939" y="128" width="37"/>
    <boldItalic x="1936" y="128" width="42"/>
  </character>
  <character uvIndex="80" character="q" byte="113" type="alphabetical">
    <regular x="3044" y="0" width="30"/>
    <bold x="3364" y="0" width="30"/>
    <italic x="2076" y="128" width="30"/>
    <boldItalic x="2073" y="128" width="36"/>
  </character>
  <character uvIndex="81" character="r" byte="114" type="alphabetical">
    <regular x="3082" y="0" width="30"/>
    <bold x="3406" y="0" width="30"/>
    <italic x="2203" y="128" width="29"/>
    <boldItalic x="2200" y="128" width="34"/>
  </character>
  <character uvIndex="82" character="s" byte="115" type="alphabetical">
    <regular x="3120" y="0" width="30"/>
    <bold x="3448" y="0" width="30"/>
    <italic x="2327" y="128" width="32"/>
    <boldItalic x="2324" y="128" width="38"/>
  </character>
  <character uvIndex="83" character="t" byte="116" type="alphabetical">
    <regular x="3158" y="0" width="30"/>
    <bold x="3490" y="0" width="30"/>
    <italic x="2463" y="128" width="20"/>
    <boldItalic x="2461" y="128" width="25"/>
  </character>
  <character uvIndex="84" character="u" byte="117" type="alphabetical">
    <regular x="3196" y="0" width="30"/>
    <bold x="3532" y="0" width="30"/>
    <italic x="2585" y="128" width="29"/>
    <boldItalic x="2583" y="128" width="34"/>
  </character>
  <character uvIndex="85" character="v" byte="118" type="alphabetical">
    <regular x="3234" y="0" width="30"/>
    <bold x="3574" y="0" width="30"/>
    <italic x="2718" y="128" width="28"/>
    <boldItalic x="2716" y="128" width="33"/>
  </character>
  <character uvIndex="86" character="w" byte="119" type="alphabetical">
    <regular x="3272" y="0" width="30"/>
    <bold x="3616" y="0" width="30"/>
    <italic x="2841" y="128" width="33"/>
    <boldItalic x="2839" y="128" width="38"/>
  </character>
  <character uvIndex="87" character="x" byte="120" type="alphabetical">
    <regular x="3310" y="0" width="30"/>
    <bold x="3658" y="0" width="30"/>
    <italic x="2967" y="128" width="31"/>
    <boldItalic x="2964" y="128" width="37"/>
  </character>
  <character uvIndex="88" character="y" byte="121" type="alphabetical">
    <regular x="3348" y="0" width="30"/>
    <bold x="3700" y="0" width="30"/>
    <italic x="3092" y="128" width="34"/>
    <boldItalic x="3090" y="128" width="39"/>
  </character>
  <character uvIndex="89" character="z" byte="122" type="alphabetical">
    <regular x="3386" y="0" width="30"/>
    <bold x="3742" y="0" width="30"/>
    <italic x="3223" y="128" width="35"/>
    <boldItalic x="3220" y="128" width="41"/>
  </character>
  <character uvIndex="90" character="{" byte="123" type="special">
    <regular x="3424" y="0" width="30"/>
    <bold x="3784" y="0" width="30"/>
    <italic x="3362" y="128" width="29"/>
    <boldItalic x="3360" y="128" width="33"/>
  </character>
  <character uvIndex="91" character="|" byte="124" type="special">
    <regular x="3462" y="0" width="30"/>
    <bold x="3826" y="0" width="30"/>
    <italic x="3489" y="128" width="20"/>
    <boldItalic x="3486" y="128" width="25"/>
  </character>
  <character uvIndex="92" character="}" byte="125" type="special">
    <regular x="3500" y="0" width="30"/>
    <bold x="3868" y="0" width="30"/>
    <italic x="3607" y="128" width="28"/>
    <boldItalic x="3605" y="128" width="32"/>
  </character>
  <character uvIndex="93" character="~" byte="126" type="special">
    <regular x="3538" y="0" width="30"/>
    <bold x="3910" y="0" width="30"/>
    <italic x="3744" y="128" width="31"/>
    <boldItalic x="3741" y="128" width="36"/>
  </character>
  <character uvIndex="94" character="¡" byte="161" type="special">
    <regular x="3576" y="0" width="30"/>
    <bold x="3952" y="0" width="30"/>
    <italic x="3873" y="128" width="20"/>
    <boldItalic x="3870" y="128" width="25"/>
  </character>
  <character uvIndex="95" character="£" byte="163" type="special">
    <regular x="3614" y="0" width="30"/>
    <bold x="3994" y="0" width="30"/>
    <italic x="3990" y="128" width="38"/>
    <boldItalic x="3988" y="128" width="42"/>
  </character>
  <character uvIndex="96" character="°" byte="176" type="special">
    <regular x="3652" y="0" width="30"/>
    <bold x="4036" y="0" width="30"/>
    <italic x="4132" y="128" width="21"/>
    <boldItalic x="4130" y="128" width="25"/>
  </character>
  <character uvIndex="97" character="±" byte="177" type="special">
    <regular x="3690" y="0" width="30"/>
    <bold x="4078" y="0" width="30"/>
    <italic x="4247" y="128" width="33"/>
    <boldItalic x="4244" y="128" width="39"/>
  </character>
  <character uvIndex="98" character="²" byte="178" type="numerical">
    <regular x="3728" y="0" width="30"/>
    <bold x="4120" y="0" width="30"/>
    <italic x="4384" y="128" width="27"/>
    <boldItalic x="4382" y="128" width="31"/>
  </character>
  <character uvIndex="99" character="³" byte="179" type="numerical">
    <regular x="3766" y="0" width="30"/>
    <bold x="4162" y="0" width="30"/>
    <italic x="4512" y="128" width="29"/>
    <boldItalic x="4510" y="128" width="33"/>
  </character>
  <character uvIndex="100" character="´" byte="180" type="special">
    <regular x="3804" y="0" width="30"/>
    <bold x="4204" y="0" width="30"/>
    <italic x="4651" y="128" width="19"/>
    <boldItalic x="4648" y="128" width="24"/>
  </character>
  <character uvIndex="101" character="¿" byte="191" type="special">
    <regular x="3842" y="0" width="30"/>
    <bold x="4246" y="0" width="30"/>
    <italic x="4760" y="128" width="29"/>
    <boldItalic x="4758" y="128" width="33"/>
  </character>
  <character uvIndex="102" character="À" byte="192" type="alphabetical">
    <regular x="3880" y="0" width="30"/>
    <bold x="4288" y="0" width="30"/>
    <italic x="4887" y="128" width="36"/>
    <boldItalic x="4884" y="128" width="41"/>
  </character>
  <character uvIndex="103" character="Á" byte="193" type="alphabetical">
    <regular x="3918" y="0" width="30"/>
    <bold x="4330" y="0" width="30"/>
    <italic x="5015" y="128" width="36"/>
    <boldItalic x="5012" y="128" width="41"/>
  </character>
  <character uvIndex="104" character="Â" byte="194" type="alphabetical">
    <regular x="3956" y="0" width="30"/>
    <bold x="4372" y="0" width="30"/>
    <italic x="5143" y="128" width="35"/>
    <boldItalic x="5140" y="128" width="40"/>
  </character>
  <character uvIndex="105" character="Ã" byte="195" type="alphabetical">
    <regular x="3994" y="0" width="30"/>
    <bold x="4414" y="0" width="30"/>
    <italic x="5271" y="128" width="42"/>
    <boldItalic x="5268" y="128" width="47"/>
  </character>
  <character uvIndex="106" character="Ä" byte="196" type="alphabetical">
    <regular x="4032" y="0" width="30"/>
    <bold x="4456" y="0" width="30"/>
    <italic x="5399" y="128" width="38"/>
    <boldItalic x="5396" y="128" width="43"/>
  </character>
  <character uvIndex="107" character="Å" byte="197" type="alphabetical">
    <regular x="4070" y="0" width="30"/>
    <bold x="4498" y="0" width="30"/>
    <italic x="5528" y="128" width="36"/>
    <boldItalic x="5525" y="128" width="41"/>
  </character>
  <character uvIndex="108" character="Æ" byte="198" type="alphabetical">
    <regular x="4108" y="0" width="30"/>
    <bold x="4540" y="0" width="30"/>
    <italic x="5656" y="128" width="40"/>
    <boldItalic x="5653" y="128" width="45"/>
  </character>
  <character uvIndex="109" character="Ç" byte="199" type="alphabetical">
    <regular x="4146" y="0" width="30"/>
    <bold x="4582" y="0" width="30"/>
    <italic x="5785" y="128" width="35"/>
    <boldItalic x="5782" y="128" width="40"/>
  </character>
  <character uvIndex="110" character="È" byte="200" type="alphabetical">
    <regular x="4184" y="0" width="30"/>
    <bold x="4624" y="0" width="30"/>
    <italic x="5911" y="128" width="37"/>
    <boldItalic x="5908" y="128" width="43"/>
  </character>
  <character uvIndex="111" character="É" byte="201" type="alphabetical">
    <regular x="4222" y="0" width="30"/>
    <bold x="4666" y="0" width="30"/>
    <italic x="6039" y="128" width="39"/>
    <boldItalic x="6036" y="128" width="44"/>
  </character>
  <character uvIndex="112" character="Ê" byte="202" type="alphabetical">
    <regular x="4260" y="0" width="30"/>
    <bold x="4708" y="0" width="30"/>
    <italic x="6167" y="128" width="37"/>
    <boldItalic x="6164" y="128" width="43"/>
  </character>
  <character uvIndex="113" character="Ë" byte="203" type="alphabetical">
    <regular x="4298" y="0" width="30"/>
    <bold x="4750" y="0" width="30"/>
    <italic x="6295" y="128" width="38"/>
    <boldItalic x="6292" y="128" width="43"/>
  </character>
  <character uvIndex="114" character="Ì" byte="204" type="alphabetical">
    <regular x="4336" y="0" width="30"/>
    <bold x="4792" y="0" width="30"/>
    <italic x="6426" y="128" width="32"/>
    <boldItalic x="6423" y="128" width="37"/>
  </character>
  <character uvIndex="115" character="Í" byte="205" type="alphabetical">
    <regular x="4374" y="0" width="30"/>
    <bold x="4834" y="0" width="30"/>
    <italic x="6554" y="128" width="32"/>
    <boldItalic x="6551" y="128" width="37"/>
  </character>
  <character uvIndex="116" character="Î" byte="206" type="alphabetical">
    <regular x="4412" y="0" width="30"/>
    <bold x="4876" y="0" width="30"/>
    <italic x="6682" y="128" width="32"/>
    <boldItalic x="6679" y="128" width="37"/>
  </character>
  <character uvIndex="117" character="Ï" byte="207" type="alphabetical">
    <regular x="4450" y="0" width="30"/>
    <bold x="4918" y="0" width="30"/>
    <italic x="6810" y="128" width="36"/>
    <boldItalic x="6807" y="128" width="41"/>
  </character>
  <character uvIndex="118" character="Ð" byte="208" type="alphabetical">
    <regular x="4488" y="0" width="30"/>
    <bold x="4960" y="0" width="30"/>
    <italic x="6935" y="128" width="35"/>
    <boldItalic x="6932" y="128" width="40"/>
  </character>
  <character uvIndex="119" character="Ñ" byte="209" type="alphabetical">
    <regular x="4526" y="0" width="30"/>
    <bold x="5002" y="0" width="30"/>
    <italic x="7063" y="128" width="42"/>
    <boldItalic x="7060" y="128" width="47"/>
  </character>
  <character uvIndex="120" character="Ò" byte="210" type="alphabetical">
    <regular x="4564" y="0" width="30"/>
    <bold x="5044" y="0" width="30"/>
    <italic x="7194" y="128" width="33"/>
    <boldItalic x="7192" y="128" width="37"/>
  </character>
  <character uvIndex="121" character="Ó" byte="211" type="alphabetical">
    <regular x="4602" y="0" width="30"/>
    <bold x="5086" y="0" width="30"/>
    <italic x="7322" y="128" width="33"/>
    <boldItalic x="7320" y="128" width="37"/>
  </character>
  <character uvIndex="122" character="Ô" byte="212" type="alphabetical">
    <regular x="4640" y="0" width="30"/>
    <bold x="5128" y="0" width="30"/>
    <italic x="7450" y="128" width="32"/>
    <boldItalic x="7448" y="128" width="36"/>
  </character>
  <character uvIndex="123" character="Õ" byte="213" type="alphabetical">
    <regular x="4678" y="0" width="30"/>
    <bold x="5170" y="0" width="30"/>
    <italic x="7578" y="128" width="36"/>
    <boldItalic x="7576" y="128" width="40"/>
  </character>
  <character uvIndex="124" character="Ö" byte="214" type="alphabetical">
    <regular x="4716" y="0" width="30"/>
    <bold x="5212" y="0" width="30"/>
    <italic x="7706" y="128" width="35"/>
    <boldItalic x="7704" y="128" width="39"/>
  </character>
  <character uvIndex="125" character="Ù" byte="217" type="alphabetical">
    <regular x="4754" y="0" width="30"/>
    <bold x="5254" y="0" width="30"/>
    <italic x="7834" y="128" width="34"/>
    <boldItalic x="7832" y="128" width="39"/>
  </character>
  <character uvIndex="126" character="Ú" byte="218" type="alphabetical">
    <regular x="4792" y="0" width="30"/>
    <bold x="5296" y="0" width="30"/>
    <italic x="7962" y="128" width="36"/>
    <boldItalic x="7960" y="128" width="40"/>
  </character>
  <character uvIndex="127" character="Û" byte="219" type="alphabetical">
    <regular x="4830" y="0" width="30"/>
    <bold x="5338" y="0" width="30"/>
    <italic x="8090" y="128" width="34"/>
    <boldItalic x="8088" y="128" width="39"/>
  </character>
  <character uvIndex="128" character="Ü" byte="220" type="alphabetical">
    <regular x="4868" y="0" width="30"/>
    <bold x="5380" y="0" width="30"/>
    <italic x="26" y="256" width="35"/>
    <boldItalic x="24" y="256" width="39"/>
  </character>
  <character uvIndex="129" character="Ý" byte="221" type="alphabetical">
    <regular x="4906" y="0" width="30"/>
    <bold x="5422" y="0" width="30"/>
    <italic x="161" y="256" width="27"/>
    <boldItalic x="158" y="256" width="33"/>
  </character>
  <character uvIndex="130" character="ß" byte="223" type="alphabetical">
    <regular x="4944" y="0" width="30"/>
    <bold x="5464" y="0" width="30"/>
    <italic x="277" y="256" width="35"/>
    <boldItalic x="274" y="256" width="40"/>
  </character>
  <character uvIndex="131" character="à" byte="224" type="alphabetical">
    <regular x="4982" y="0" width="30"/>
    <bold x="5506" y="0" width="30"/>
    <italic x="408" y="256" width="33"/>
    <boldItalic x="406" y="256" width="37"/>
  </character>
  <character uvIndex="132" character="á" byte="225" type="alphabetical">
    <regular x="5020" y="0" width="30"/>
    <bold x="5548" y="0" width="30"/>
    <italic x="536" y="256" width="33"/>
    <boldItalic x="534" y="256" width="37"/>
  </character>
  <character uvIndex="133" character="â" byte="226" type="alphabetical">
    <regular x="5058" y="0" width="30"/>
    <bold x="5590" y="0" width="30"/>
    <italic x="665" y="256" width="34"/>
    <boldItalic x="663" y="256" width="38"/>
  </character>
  <character uvIndex="134" character="ã" byte="227" type="alphabetical">
    <regular x="5096" y="0" width="30"/>
    <bold x="5632" y="0" width="30"/>
    <italic x="792" y="256" width="41"/>
    <boldItalic x="790" y="256" width="45"/>
  </character>
  <character uvIndex="135" character="ä" byte="228" type="alphabetical">
    <regular x="5134" y="0" width="30"/>
    <bold x="5674" y="0" width="30"/>
    <italic x="920" y="256" width="35"/>
    <boldItalic x="918" y="256" width="39"/>
  </character>
  <character uvIndex="136" character="å" byte="229" type="alphabetical">
    <regular x="5172" y="0" width="30"/>
    <bold x="5716" y="0" width="30"/>
    <italic x="1048" y="256" width="35"/>
    <boldItalic x="1046" y="256" width="39"/>
  </character>
  <character uvIndex="137" character="æ" byte="230" type="alphabetical">
    <regular x="5210" y="0" width="30"/>
    <bold x="5758" y="0" width="30"/>
    <italic x="1176" y="256" width="33"/>
    <boldItalic x="1174" y="256" width="37"/>
  </character>
  <character uvIndex="138" character="ç" byte="231" type="alphabetical">
    <regular x="5248" y="0" width="30"/>
    <bold x="5800" y="0" width="30"/>
    <italic x="1305" y="256" width="31"/>
    <boldItalic x="1302" y="256" width="36"/>
  </character>
  <character uvIndex="139" character="è" byte="232" type="alphabetical">
    <regular x="5286" y="0" width="30"/>
    <bold x="5842" y="0" width="30"/>
    <italic x="1434" y="256" width="31"/>
    <boldItalic x="1432" y="256" width="35"/>
  </character>
  <character uvIndex="140" character="é" byte="233" type="alphabetical">
    <regular x="5324" y="0" width="30"/>
    <bold x="5884" y="0" width="30"/>
    <italic x="1562" y="256" width="31"/>
    <boldItalic x="1560" y="256" width="35"/>
  </character>
  <character uvIndex="141" character="ê" byte="234" type="alphabetical">
    <regular x="5362" y="0" width="30"/>
    <bold x="5926" y="0" width="30"/>
    <italic x="1690" y="256" width="33"/>
    <boldItalic x="1688" y="256" width="37"/>
  </character>
  <character uvIndex="142" character="ë" byte="235" type="alphabetical">
    <regular x="5400" y="0" width="30"/>
    <bold x="5968" y="0" width="30"/>
    <italic x="1818" y="256" width="34"/>
    <boldItalic x="1816" y="256" width="38"/>
  </character>
  <character uvIndex="143" character="ì" byte="236" type="alphabetical">
    <regular x="5438" y="0" width="30"/>
    <bold x="6010" y="0" width="30"/>
    <italic x="1946" y="256" width="27"/>
    <boldItalic x="1943" y="256" width="32"/>
  </character>
  <character uvIndex="144" character="í" byte="237" type="alphabetical">
    <regular x="5476" y="0" width="30"/>
    <bold x="6052" y="0" width="30"/>
    <italic x="2074" y="256" width="30"/>
    <boldItalic x="2071" y="256" width="35"/>
  </character>
  <character uvIndex="145" character="î" byte="238" type="alphabetical">
    <regular x="5514" y="0" width="30"/>
    <bold x="6094" y="0" width="30"/>
    <italic x="2202" y="256" width="32"/>
    <boldItalic x="2199" y="256" width="37"/>
  </character>
  <character uvIndex="146" character="ï" byte="239" type="alphabetical">
    <regular x="5552" y="0" width="30"/>
    <bold x="6136" y="0" width="30"/>
    <italic x="2330" y="256" width="33"/>
    <boldItalic x="2327" y="256" width="38"/>
  </character>
  <character uvIndex="147" character="ð" byte="240" type="alphabetical">
    <regular x="5590" y="0" width="30"/>
    <bold x="6178" y="0" width="30"/>
    <italic x="2458" y="256" width="33"/>
    <boldItalic x="2456" y="256" width="37"/>
  </character>
  <character uvIndex="148" character="ñ" byte="241" type="alphabetical">
    <regular x="5628" y="0" width="30"/>
    <bold x="6220" y="0" width="30"/>
    <italic x="2583" y="256" width="39"/>
    <boldItalic x="2580" y="256" width="44"/>
  </character>
  <character uvIndex="149" character="ò" byte="242" type="alphabetical">
    <regular x="5666" y="0" width="30"/>
    <bold x="6262" y="0" width="30"/>
    <italic x="2714" y="256" width="31"/>
    <boldItalic x="2712" y="256" width="35"/>
  </character>
  <character uvIndex="150" character="ó" byte="243" type="alphabetical">
    <regular x="5704" y="0" width="30"/>
    <bold x="6304" y="0" width="30"/>
    <italic x="2842" y="256" width="31"/>
    <boldItalic x="2840" y="256" width="35"/>
  </character>
  <character uvIndex="151" character="ô" byte="244" type="alphabetical">
    <regular x="5742" y="0" width="30"/>
    <bold x="6346" y="0" width="30"/>
    <italic x="2970" y="256" width="32"/>
    <boldItalic x="2968" y="256" width="36"/>
  </character>
  <character uvIndex="152" character="õ" byte="245" type="alphabetical">
    <regular x="5780" y="0" width="30"/>
    <bold x="6388" y="0" width="30"/>
    <italic x="3098" y="256" width="36"/>
    <boldItalic x="3096" y="256" width="40"/>
  </character>
  <character uvIndex="153" character="ö" byte="246" type="alphabetical">
    <regular x="5818" y="0" width="30"/>
    <bold x="6430" y="0" width="30"/>
    <italic x="3226" y="256" width="33"/>
    <boldItalic x="3224" y="256" width="37"/>
  </character>
  <character uvIndex="154" character="÷" byte="247" type="special">
    <regular x="5856" y="0" width="30"/>
    <bold x="6472" y="0" width="30"/>
    <italic x="3357" y="256" width="27"/>
    <boldItalic x="3355" y="256" width="32"/>
  </character>
  <character uvIndex="155" character="ø" byte="248" type="alphabetical">
    <regular x="5894" y="0" width="30"/>
    <bold x="6514" y="0" width="30"/>
    <italic x="3477" y="256" width="39"/>
    <boldItalic x="3474" y="256" width="45"/>
  </character>
  <character uvIndex="156" character="ù" byte="249" type="alphabetical">
    <regular x="5932" y="0" width="30"/>
    <bold x="6556" y="0" width="30"/>
    <italic x="3609" y="256" width="29"/>
    <boldItalic x="3607" y="256" width="34"/>
  </character>
  <character uvIndex="157" character="ú" byte="250" type="alphabetical">
    <regular x="5970" y="0" width="30"/>
    <bold x="6598" y="0" width="30"/>
    <italic x="3737" y="256" width="31"/>
    <boldItalic x="3735" y="256" width="35"/>
  </character>
  <character uvIndex="158" character="û" byte="251" type="alphabetical">
    <regular x="6008" y="0" width="30"/>
    <bold x="6640" y="0" width="30"/>
    <italic x="3865" y="256" width="33"/>
    <boldItalic x="3863" y="256" width="37"/>
  </character>
  <character uvIndex="159" character="ü" byte="252" type="alphabetical">
    <regular x="6046" y="0" width="30"/>
    <bold x="6682" y="0" width="30"/>
    <italic x="3993" y="256" width="34"/>
    <boldItalic x="3991" y="256" width="38"/>
  </character>
  <character uvIndex="160" character="ý" byte="253" type="alphabetical">
    <regular x="6084" y="0" width="30"/>
    <bold x="6724" y="0" width="30"/>
    <italic x="4116" y="256" width="36"/>
    <boldItalic x="4114" y="256" width="40"/>
  </character>
  <character uvIndex="161" character="ÿ" byte="255" type="alphabetical">
    <regular x="6122" y="0" width="30"/>
    <bold x="6766" y="0" width="30"/>
    <italic x="4244" y="256" width="39"/>
    <boldItalic x="4242" y="256" width="43"/>
  </character>
  <character uvIndex="162" character="Ā" byte="256" type="alphabetical">
    <regular x="6160" y="0" width="30"/>
    <bold x="6808" y="0" width="30"/>
    <italic x="4375" y="256" width="38"/>
    <boldItalic x="4372" y="256" width="43"/>
  </character>
  <character uvIndex="163" character="ā" byte="257" type="alphabetical">
    <regular x="6198" y="0" width="30"/>
    <bold x="6850" y="0" width="30"/>
    <italic x="4504" y="256" width="35"/>
    <boldItalic x="4502" y="256" width="39"/>
  </character>
  <character uvIndex="164" character="Ă" byte="258" type="alphabetical">
    <regular x="6236" y="0" width="30"/>
    <bold x="6892" y="0" width="30"/>
    <italic x="4631" y="256" width="38"/>
    <boldItalic x="4628" y="256" width="43"/>
  </character>
  <character uvIndex="165" character="ă" byte="259" type="alphabetical">
    <regular x="6274" y="0" width="30"/>
    <bold x="6934" y="0" width="30"/>
    <italic x="4760" y="256" width="37"/>
    <boldItalic x="4758" y="256" width="41"/>
  </character>
</font>
